PyQt5/Qt5/qsci/api/python/PyQtWebEngine.api
PyQt5/QtWebEngine.abi3.so
PyQt5/QtWebEngine.pyi
PyQt5/QtWebEngineCore.abi3.so
PyQt5/QtWebEngineCore.pyi
PyQt5/QtWebEngineWidgets.abi3.so
PyQt5/QtWebEngineWidgets.pyi
PyQt5/bindings/QtWebEngine/QtWebEngine.toml
PyQt5/bindings/QtWebEngine/QtWebEnginemod.sip
PyQt5/bindings/QtWebEngine/qquickwebengineprofile.sip
PyQt5/bindings/QtWebEngine/qquickwebenginescript.sip
PyQt5/bindings/QtWebEngine/qtwebengineglobal.sip
PyQt5/bindings/QtWebEngineCore/QtWebEngineCore.toml
PyQt5/bindings/QtWebEngineCore/QtWebEngineCoremod.sip
PyQt5/bindings/QtWebEngineCore/qwebengineclientcertificatestore.sip
PyQt5/bindings/QtWebEngineCore/qwebenginecookiestore.sip
PyQt5/bindings/QtWebEngineCore/qwebenginefindtextresult.sip
PyQt5/bindings/QtWebEngineCore/qwebenginehttprequest.sip
PyQt5/bindings/QtWebEngineCore/qwebenginenotification.sip
PyQt5/bindings/QtWebEngineCore/qwebenginequotarequest.sip
PyQt5/bindings/QtWebEngineCore/qwebengineregisterprotocolhandlerrequest.sip
PyQt5/bindings/QtWebEngineCore/qwebengineurlrequestinfo.sip
PyQt5/bindings/QtWebEngineCore/qwebengineurlrequestinterceptor.sip
PyQt5/bindings/QtWebEngineCore/qwebengineurlrequestjob.sip
PyQt5/bindings/QtWebEngineCore/qwebengineurlscheme.sip
PyQt5/bindings/QtWebEngineCore/qwebengineurlschemehandler.sip
PyQt5/bindings/QtWebEngineWidgets/QtWebEngineWidgets.toml
PyQt5/bindings/QtWebEngineWidgets/QtWebEngineWidgetsmod.sip
PyQt5/bindings/QtWebEngineWidgets/qwebenginecertificateerror.sip
PyQt5/bindings/QtWebEngineWidgets/qwebengineclientcertificateselection.sip
PyQt5/bindings/QtWebEngineWidgets/qwebenginecontextmenudata.sip
PyQt5/bindings/QtWebEngineWidgets/qwebenginedownloaditem.sip
PyQt5/bindings/QtWebEngineWidgets/qwebenginefullscreenrequest.sip
PyQt5/bindings/QtWebEngineWidgets/qwebenginehistory.sip
PyQt5/bindings/QtWebEngineWidgets/qwebenginepage.sip
PyQt5/bindings/QtWebEngineWidgets/qwebengineprofile.sip
PyQt5/bindings/QtWebEngineWidgets/qwebenginescript.sip
PyQtWebEngine-5.15.7.dist-info/WHEEL
PyQtWebEngine-5.15.7.dist-info/METADATA
PyQtWebEngine-5.15.7.dist-info/RECORD
