Metadata-Version: 2.1
Name: PyQtWebEngine
Version: 5.15.7
Requires-Python: >=3.8
Summary: Python bindings for the Qt WebEngine framework
Project-Url: homepage, https://www.riverbankcomputing.com/software/pyqtwebengine/
Requires-Dist: PyQt5 (>=5.15.4)
License: GPL v3
Author-Email: Riverbank Computing Limited <info@riverbankcomputing.com>
